trifast/__init__.py
trifast/autotune.py
trifast/autotune_helpers.py
trifast/equiv.py
trifast/torch.py
trifast/triton.py
trifast/tune.py
trifast/utils.py
trifast-0.1.13.dist-info/METADATA
trifast-0.1.13.dist-info/WHEEL
trifast-0.1.13.dist-info/entry_points.txt
trifast-0.1.13.dist-info/licenses/LICENSE
trifast-0.1.13.dist-info/RECORD
