Metadata-Version: 2.4
Name: trifast
Version: 0.1.13
Summary: Fast kernel for triangle self attetion.
Author-email: Liam Atkinson <hello@liamatkinson.com>
License-File: LICENSE
Requires-Python: >=3.10
Requires-Dist: einops>=0.8.0
Requires-Dist: jaxtyping>=0.2.36
Requires-Dist: numpy>=1.26.3
Requires-Dist: platformdirs>=4.3.6
Requires-Dist: pyyaml>=6.0.2
Requires-Dist: setuptools>=75.6.0
Requires-Dist: torch>=2.6.0
Requires-Dist: triton>=3.1.0
Provides-Extra: benchmark
Requires-Dist: deepspeed>=0.16.0; extra == 'benchmark'
Provides-Extra: test
Requires-Dist: pytest>=8.3.4; extra == 'test'
